yolo_screen_stream/__init__.py
yolo_screen_stream/processor.py
yolo_screen_stream-1.0.8.dist-info/METADATA
yolo_screen_stream-1.0.8.dist-info/WHEEL
yolo_screen_stream-1.0.8.dist-info/top_level.txt
yolo_screen_stream-1.0.8.dist-info/RECORD
